txoids/__init__.py
txoids/engine.py
txoids/utils.py
txoids/cable_diag/__init__.py
txoids/cable_diag/deferreds.py
txoids/cable_diag/oids.py
txoids/cable_diag/processors.py
txoids/generic/__init__.py
txoids/generic/deferreds.py
txoids/generic/processors.py
txoids/igmp/__init__.py
txoids/igmp/deferreds.py
txoids/igmp/oids.py
txoids/igmp/processors.py
txoids/ports/__init__.py
txoids/ports/deferreds.py
txoids/ports/oids.py
txoids/ports/processors.py
txoids-0.1.14.dist-info/DESCRIPTION.rst
txoids-0.1.14.dist-info/METADATA
txoids-0.1.14.dist-info/RECORD
txoids-0.1.14.dist-info/WHEEL
txoids-0.1.14.dist-info/metadata.json
txoids-0.1.14.dist-info/top_level.txt
