Metadata-Version: 2.0
Name: txoids
Version: 0.1.14
Summary: Tool for parsing switches using SNMP
Home-page: https://github.com/kalombos/txoids
Author: kalombo
Author-email: nogamemorebrain@gmail.com
License: UNKNOWN
Download-URL: https://github.com/kalombos/txoids
Keywords: snmp,twisted,pynetsnmp,netsnmp
Platform: UNKNOWN
Requires-Dist: pynetsnmp-2
